setup.py
json_test/__init__.py
json_test/json_check.py
json_test/jvalue.py
json_test/test_json_check.py
json_test.egg-info/PKG-INFO
json_test.egg-info/SOURCES.txt
json_test.egg-info/dependency_links.txt
json_test.egg-info/not-zip-safe
json_test.egg-info/pbr.json
json_test.egg-info/top_level.txt