Metadata-Version: 1.0
Name: json-test
Version: 0.1
Summary: A python library for assisting you in writing tests against a JSON structure.
Home-page: https://github.com/inkmonk/json-test
Author: Sibi
Author-email: sibi@psibi.in
License: BSD3
Platform: UNKNOWN
